llm_common/__init__.py
llm_common/prometheus.py
llm_common/py.typed
llm_common/clients/__init__.py
llm_common/clients/aiohttp_client.py
llm_common/clients/auth_client.py
llm_common/clients/httpx_client.py
llm_common/clients/llm_http_client.py
llm_common/clients/telegram_client.py
llm_common-2.2.0.dist-info/METADATA
llm_common-2.2.0.dist-info/WHEEL
llm_common-2.2.0.dist-info/top_level.txt
llm_common-2.2.0.dist-info/RECORD
