Metadata-Version: 2.4
Name: llm_common
Version: 2.2.0
Author-email: Pavel Maksimov <pavel.maximov@megafon.ru>
Requires-Python: >=3.11
